[
    {
        "id": "47cf49f6-bddf-479e-89b2-a2860ae6d520",
        "actor_id": "admin-test",
        "actor_role": "admin",
        "merchant_id": "test-feat-merchant",
        "action": "refund_created",
        "description": "Refund partial Rp 10.000 for order FEAT-TEST-001",
        "ip": "0.0.0.0",
        "user_agent": "Unknown",
        "metadata": {
            "refund_id": "b3825528-0eaa-42aa-8afd-6536d1a1b053",
            "transaction_id": "tx-feat-test",
            "amount": 10000,
            "reason": "Partial refund test"
        },
        "created_at": "2026-07-07 12:30:20"
    }
]